rfm/__init__.py
rfm/rfm.py
rfm-1.0.9.dist-info/LICENSE
rfm-1.0.9.dist-info/METADATA
rfm-1.0.9.dist-info/WHEEL
rfm-1.0.9.dist-info/top_level.txt
rfm-1.0.9.dist-info/RECORD
