Metadata-Version: 2.1
Name: rfm
Version: 1.0.9
Summary: Python Package for RFM Analysis and Customer Segmentation
Home-page: https://github.com/sonwanesuresh95/rfm
Author: Suresh Sonwane
Author-email: sonwanesuresh739@gmail.com
License: UNKNOWN
Project-URL: Bug Tracker, https://github.com/sonwanesuresh95/rfm/issues
Platform: UNKNOWN
Classifier: Programming Language :: Python :: 3
Classifier: License :: OSI Approved :: MIT License
Classifier: Operating System :: OS Independent
Requires-Python: >=3.6
License-File: LICENSE
Requires-Dist: pandas (>=1.2.4)
Requires-Dist: numpy (>=1.20.1)
Requires-Dist: matplotlib (>=3.3.4)
